hooqu/__init__.py
hooqu/checks.py
hooqu/dataframe.py
hooqu/metrics.py
hooqu/verification_suite.py
hooqu/_typing/__init__.py
hooqu/_typing/protocols/__init__.py
hooqu/_typing/protocols/frame.py
hooqu/_typing/protocols/series.py
hooqu/analyzers/__init__.py
hooqu/analyzers/analyzer.py
hooqu/analyzers/completeness.py
hooqu/analyzers/compliance.py
hooqu/analyzers/grouping_analyzers.py
hooqu/analyzers/maximum.py
hooqu/analyzers/mean.py
hooqu/analyzers/minimum.py
hooqu/analyzers/preconditions.py
hooqu/analyzers/quantile.py
hooqu/analyzers/size.py
hooqu/analyzers/standard_deviation.py
hooqu/analyzers/sum.py
hooqu/analyzers/uniqueness.py
hooqu/analyzers/runners/__init__.py
hooqu/analyzers/runners/analysis_runner.py
hooqu/constraints/__init__.py
hooqu/constraints/analysis_based_constraint.py
hooqu/constraints/constraint.py
hooqu/constraints/constraints.py
hooqu/tests/__init__.py
hooqu/tests/conftest.py
hooqu/tests/fixtures.py
hooqu/tests/test_analysis_runner.py
hooqu/tests/test_analyzers.py
hooqu/tests/test_check.py
hooqu/tests/test_constraint.py
hooqu/tests/test_grouping_analyzers.py
hooqu/tests/test_metrics.py
hooqu/tests/test_sample.py
hooqu/tests/test_uniqueness.py
hooqu/tests/test_verification_suite.py
hooqu-0.1.0.dist-info/AUTHORS.rst
hooqu-0.1.0.dist-info/LICENSE
hooqu-0.1.0.dist-info/METADATA
hooqu-0.1.0.dist-info/WHEEL
hooqu-0.1.0.dist-info/top_level.txt
hooqu-0.1.0.dist-info/RECORD
