Metadata-Version: 2.1
Name: hooqu
Version: 0.1.0
Summary: Data unit testing for your Python DataFrames
Home-page: https://github.com/mfcabrera/hooqu
Author: Miguel Cabrera
Author-email: mfcabrera@gmail.com
License: Apache Software License 2.0
Keywords: hooqu
Platform: UNKNOWN
Classifier: Programming Language :: Python :: 3
Classifier: Development Status :: 3 - Alpha
Classifier: Intended Audience :: Developers
Classifier: Operating System :: OS Independent
Classifier: License :: OSI Approved :: Apache Software License
Classifier: Programming Language :: Python :: 3.7
Classifier: Programming Language :: Python :: 3.8
Classifier: Topic :: Scientific/Engineering
Classifier: Topic :: System :: Monitoring
Requires-Python: >=3.7
Requires-Dist: pandas (>=1.0.0)
Requires-Dist: tryingsnake (>=0.5.0)
Requires-Dist: more-itertools (>=8.2.0)
Requires-Dist: typing-extensions
Provides-Extra: testing
Requires-Dist: pip (==20.1.1) ; extra == 'testing'
Requires-Dist: punch.py (==2.0.0) ; extra == 'testing'
Requires-Dist: wheel (==0.34.2) ; extra == 'testing'
Requires-Dist: watchdog (==0.10.3) ; extra == 'testing'
Requires-Dist: flake8 (==3.8.3) ; extra == 'testing'
Requires-Dist: Sphinx (==3.2.1) ; extra == 'testing'
Requires-Dist: PyYAML (==5.3.1) ; extra == 'testing'
Requires-Dist: tox (==3.19.0) ; extra == 'testing'
Requires-Dist: coverage (==5.2) ; extra == 'testing'
Requires-Dist: pytest (==5.4.3) ; extra == 'testing'
Requires-Dist: pytest-cov (==2.10.0) ; extra == 'testing'
Requires-Dist: black (==19.10b0) ; extra == 'testing'
Requires-Dist: hypothesis (==5.29.0) ; extra == 'testing'
Requires-Dist: mypy (==0.782) ; extra == 'testing'
Requires-Dist: mypy-extensions (==0.4.3) ; extra == 'testing'
Requires-Dist: codecov (==2.1.9) ; extra == 'testing'
